odoo/addons/account_analytic_required/README.rst
odoo/addons/account_analytic_required/__init__.py
odoo/addons/account_analytic_required/__manifest__.py
odoo/addons/account_analytic_required/i18n/account_analytic_required.pot
odoo/addons/account_analytic_required/i18n/ar.po
odoo/addons/account_analytic_required/i18n/ca.po
odoo/addons/account_analytic_required/i18n/de.po
odoo/addons/account_analytic_required/i18n/es.po
odoo/addons/account_analytic_required/i18n/es_CO.po
odoo/addons/account_analytic_required/i18n/fr.po
odoo/addons/account_analytic_required/i18n/hr_HR.po
odoo/addons/account_analytic_required/i18n/nl.po
odoo/addons/account_analytic_required/i18n/pt_BR.po
odoo/addons/account_analytic_required/models/__init__.py
odoo/addons/account_analytic_required/models/account.py
odoo/addons/account_analytic_required/static/description/icon.png
odoo/addons/account_analytic_required/tests/__init__.py
odoo/addons/account_analytic_required/tests/test_account_analytic_required.py
odoo/addons/account_analytic_required/views/account.xml
odoo11_addon_account_analytic_required-11.0.1.0.0.99.dev14.dist-info/METADATA
odoo11_addon_account_analytic_required-11.0.1.0.0.99.dev14.dist-info/RECORD
odoo11_addon_account_analytic_required-11.0.1.0.0.99.dev14.dist-info/WHEEL
odoo11_addon_account_analytic_required-11.0.1.0.0.99.dev14.dist-info/top_level.txt
